de_sherlock/__init__.py
de_sherlock/api_step.py
de_sherlock/description_step.py
de_sherlock/elastic_step.py
de_sherlock/kafka_step.py
de_sherlock/oracle_step.py
de_sherlock/prepare_steps.py
de_sherlock/transform_step.py
de_sherlock/creds/__init__.py
de_sherlock/intializer/__init__.py
de_sherlock/intializer/step_initializer.py
de_sherlock/utils/__init__.py
de_sherlock/utils/pvc_intigration.py
de_sherlock-0.1.2.dist-info/METADATA
de_sherlock-0.1.2.dist-info/WHEEL
de_sherlock-0.1.2.dist-info/top_level.txt
de_sherlock-0.1.2.dist-info/RECORD
